pynatrace/__init__.py
pynatrace/cli.py
pynatrace/helper.py
pynatrace-1.11.0.dist-info/LICENSE
pynatrace-1.11.0.dist-info/METADATA
pynatrace-1.11.0.dist-info/WHEEL
pynatrace-1.11.0.dist-info/entry_points.txt
pynatrace-1.11.0.dist-info/RECORD
