Metadata-Version: 2.1
Name: pynatrace
Version: 1.11.0
Summary: Python limited CLI for Dynatrace
License: MIT
Author: Michael MacKenna
Author-email: mmackenna@unitedfiregroup.com
Requires-Python: >=3.11,<4.0
Classifier: License :: OSI Approved :: MIT License
Classifier: Programming Language :: Python :: 3
Classifier: Programming Language :: Python :: 3.11
Classifier: Programming Language :: Python :: 3.12
Requires-Dist: click (>=8.1.3,<9.0.0)
Requires-Dist: dt (>=1.1.48,<2.0.0)
Requires-Dist: requests (>=2.27.1,<3.0.0)
Requires-Dist: termcolor (>=2.2.0,<3.0.0)
